odoo/addons/base_geolocalize_company/README.rst
odoo/addons/base_geolocalize_company/__init__.py
odoo/addons/base_geolocalize_company/__manifest__.py
odoo/addons/base_geolocalize_company/demo/res_company.xml
odoo/addons/base_geolocalize_company/i18n/base_geolocalize_company.pot
odoo/addons/base_geolocalize_company/i18n/fr.po
odoo/addons/base_geolocalize_company/models/__init__.py
odoo/addons/base_geolocalize_company/models/res_company.py
odoo/addons/base_geolocalize_company/readme/CONTRIBUTORS.rst
odoo/addons/base_geolocalize_company/readme/DESCRIPTION.rst
odoo/addons/base_geolocalize_company/static/description/icon.png
odoo/addons/base_geolocalize_company/static/description/index.html
odoo/addons/base_geolocalize_company/static/description/res_company_form.png
odoo/addons/base_geolocalize_company/views/view_res_company.xml
odoo12_addon_base_geolocalize_company-12.0.1.0.1.99.dev4.dist-info/METADATA
odoo12_addon_base_geolocalize_company-12.0.1.0.1.99.dev4.dist-info/WHEEL
odoo12_addon_base_geolocalize_company-12.0.1.0.1.99.dev4.dist-info/top_level.txt
odoo12_addon_base_geolocalize_company-12.0.1.0.1.99.dev4.dist-info/RECORD
